__init__.py
drops/__init__.py
drops/drops.py
drops/console/__init__.py
drops/console/main.py
drops/console/main_test.py
drops/console/test.py
drops/console/test_biz.py
drops/console/test_cmd.py
drops/console/test_config.py
drops/console/test_lib.py
drops/console/pkg/__init__.py
drops/console/pkg/biz.py
drops/console/pkg/cmd.py
drops/console/pkg/config.py
drops/console/pkg/er.py
drops/console/pkg/globa.py
drops/console/pkg/helper.py
drops/console/pkg/log.py
drops/console/pkg/system.py
drops/console/pkg/version.py
drops/docker_ops/.gitignore
drops/docker_ops/docker-compose.yaml
drops/docker_ops/release/README.md
drops/docker_ops/release/web/index.html
drops/docker_ops/script/init.sh
drops/docker_ops/secret/README.sh
drops/docker_ops/secret/ssh/known_hosts
drops/docker_ops/servers/README.md
drops/docker_ops/servers/acme.sh/redeploy-ssl
drops/docker_ops/servers/drops/README.md
drops/docker_ops/servers/drops/bin/.keep
drops/docker_ops/servers/drops/cron/daily/.gitkeep
drops/docker_ops/servers/drops/cron/hourly/.gitkeep
drops/docker_ops/servers/drops/cron/monthly/.gitkeep
drops/docker_ops/servers/drops/cron/weekly/.gitkeep
drops/docker_ops/servers/drops/cron_example/README.md
drops/docker_ops/servers/drops/cron_example/backup.sh
drops/docker_ops/servers/drops/cron_example/backupdb.sh
drops/docker_ops/servers/drops/cron_example/drops-backup.py
drops/docker_ops/servers/drops/drops/README.sh
drops/docker_ops/servers/nginx/nginx.conf
drops/docker_ops/servers/nginx/auth_basic/metrics.pwd
drops/docker_ops/servers/nginx/conf.d/drops.conf
drops/docker_ops/servers/nginx/lib/gzip.conf
drops/docker_ops/servers/nginx/lib/metrics.conf
drops/docker_ops/servers/nginx/lib/referer.conf
drops/docker_ops/servers/nginx/lib/ssl.conf
drops/docker_ops/servers/nginx/lib/tohttps.conf
drops/docker_ops/src/server/go.mod
drops/docker_ops/src/server/cmd/drops/main.go
drops/docker_ops/src/server/cmd/te/main.go
drops/docker_ops/src/server/drops/build.py
drops/docker_ops/src/web/index.html
drops-1.1.10.dist-info/licenses/LICENSE
drops-1.1.10.dist-info/METADATA
drops-1.1.10.dist-info/WHEEL
drops-1.1.10.dist-info/entry_points.txt
drops-1.1.10.dist-info/top_level.txt
drops-1.1.10.dist-info/RECORD
