Metadata-Version: 2.4
Name: drops
Version: 1.1.10
Summary: drops 是基于 ssh 和 docker-compose 的运维模板，附带的 drops 命令可以方便的管理项目，部署服务。
Author-email: szerr <i@szerr.org>
License:                     GNU GENERAL PUBLIC LICENSE
Project-URL: Homepage, https://github.com/szerr/drops
Project-URL: Bug Tracker, https://github.com/szerr/drops/issues
Classifier: Programming Language :: Python :: 3
Classifier: License :: OSI Approved :: GNU General Public License v3 or later (GPLv3+)
Classifier: Operating System :: OS Independent
Requires-Python: >=3.9
License-File: LICENSE
Requires-Dist: pyyaml>=5.3
Requires-Dist: paramiko>=2.12
Requires-Dist: watchdog>=3.0.0
Dynamic: license-file
